__init__.py
tools/__init__.py
tools/version_grabber.py
SparkTools-0.0.2.dist-info/LICENSE
SparkTools-0.0.2.dist-info/METADATA
SparkTools-0.0.2.dist-info/WHEEL
SparkTools-0.0.2.dist-info/top_level.txt
SparkTools-0.0.2.dist-info/RECORD
