Metadata-Version: 2.1
Name: SparkTools
Version: 0.0.2
Summary: Spark tools
Author-email: Victor Daniel Gil Becerra <victordyil97@gmail.com>
License: Attribution 4.0 International
Project-URL: Homepage, https://github.com/victoryil/Spark-tools
Project-URL: Bug Tracker, https://github.com/victoryil/Spark-tools/issues
Classifier: Programming Language :: Python :: 3
Classifier: License :: OSI Approved :: MIT License
Classifier: Operating System :: OS Independent
Requires-Python: >=3.7
License-File: LICENSE
